<item>
    <title>[B][COLORred]13Clowns[/COLOR] COPA[/B]</title>
    <thumbnail>https://psplsoccer.demosphere-secure.com/_files/events-info/wa-copa-cup-2019/Copa%20Cup.png</thumbnail>
    <fanart>http://as01.epimg.net/futbol/imagenes/2017/05/18/uefa/1495075604_388074_1495075972_noticia_normal.jpg</fanart>
</item>
<item>
    <title>[B][COLORyellow]13Clowns[/COLOR] WISHING ALL FATHERS A HAPPY FATHERS DAY[/B]</title>
    <thumbnail>https://i.pinimg.com/originals/13/40/4d/13404dcc69673133de061de8ab438695.jpg</thumbnail>
    <fanart>https://images.indianexpress.com/2019/06/fathers-day-2019_4.jpg</fanart>
</item>
<item>
    <title>Copa Mundial Femenina de la FIFA Francia 2019: USA vs. Chile [COLORyellow]08:30PST[/COLOR]</title>
    <link>
        <sublink>http://cdn3.hdstreams.club/live/ch7/index.m3u8|User-Agent=Mozilla/5.0 (Windows NT 10.0; Win64; x64; rv:67.0) Gecko/20100101 Firefox/67.0&Referer=http://hdstreams.club/page/ch7.php</sublink>
        <sublink>plugin://plugin.video.SportsDevil/?mode=1&amp;amp;item=catcher%3dstreams%26url=http://www.sports-stream.net/ch.php?id=1</sublink>
    </link>
    <thumbnail>https://psplsoccer.demosphere-secure.com/_files/events-info/wa-copa-cup-2019/Copa%20Cup.png</thumbnail>
    <fanart>http://as01.epimg.net/futbol/imagenes/2017/05/18/uefa/1495075604_388074_1495075972_noticia_normal.jpg</fanart>
</item>
<item>
    <title>Fútbol: Copa América Brasil 2019: Paraguay vs. Qatar [COLORyellow]11:30PST[/COLOR]</title>
    <link>
        <sublink>http://cdn3.hdstreams.club/live/ch1/index.m3u8|User-Agent=Mozilla/5.0 (Windows NT 10.0; Win64; x64; rv:67.0) Gecko/20100101 Firefox/67.0&Referer=http://hdstreams.club/page/ch1.php</sublink>
        <sublink>plugin://plugin.video.SportsDevil/?mode=1&amp;amp;item=catcher%3dstreams%26url=http://www.sports-stream.net/ch.php?id=15</sublink>
    </link>
    <thumbnail>https://psplsoccer.demosphere-secure.com/_files/events-info/wa-copa-cup-2019/Copa%20Cup.png</thumbnail>
    <fanart>http://as01.epimg.net/futbol/imagenes/2017/05/18/uefa/1495075604_388074_1495075972_noticia_normal.jpg</fanart>
</item>
<item>
    <title>Fútbol: Concacaf Copa Oro 2019: Haití vs. Bermuda [COLORyellow]14:30PST[/COLOR]</title>
    <link>
        <sublink>http://cdn3.hdstreams.club/live/ch4/index.m3u8|User-Agent=Mozilla/5.0 (Windows NT 10.0; Win64; x64; rv:67.0) Gecko/20100101 Firefox/67.0&Referer=http://hdstreams.club/page/ch4.php</sublink>
    </link>
    <thumbnail>https://psplsoccer.demosphere-secure.com/_files/events-info/wa-copa-cup-2019/Copa%20Cup.png</thumbnail>
    <fanart>http://as01.epimg.net/futbol/imagenes/2017/05/18/uefa/1495075604_388074_1495075972_noticia_normal.jpg</fanart>
</item>
<item>
    <title>Fútbol: Copa América Brasil 2019: Uruguay vs. Ecuador [COLORyellow]14:30PST[/COLOR]</title>
    <link>
        <sublink>http://cdn3.hdstreams.club/live/ch1/index.m3u8|User-Agent=Mozilla/5.0 (Windows NT 10.0; Win64; x64; rv:67.0) Gecko/20100101 Firefox/67.0&Referer=http://hdstreams.club/page/ch1.php</sublink>
    </link>
    <thumbnail>https://psplsoccer.demosphere-secure.com/_files/events-info/wa-copa-cup-2019/Copa%20Cup.png</thumbnail>
    <fanart>http://as01.epimg.net/futbol/imagenes/2017/05/18/uefa/1495075604_388074_1495075972_noticia_normal.jpg</fanart>
</item>
<item>
    <title>Fútbol: Concacaf Copa Oro 2019: Costa Rica vs. Nicaragua [COLORyellow]17:00PST[/COLOR]</title>
    <link>
        <sublink>http://cdn3.hdstreams.club/live/ch4/index.m3u8|User-Agent=Mozilla/5.0 (Windows NT 10.0; Win64; x64; rv:67.0) Gecko/20100101 Firefox/67.0&Referer=http://hdstreams.club/page/ch4.php</sublink>
    </link>
    <thumbnail>https://psplsoccer.demosphere-secure.com/_files/events-info/wa-copa-cup-2019/Copa%20Cup.png</thumbnail>
    <fanart>http://as01.epimg.net/futbol/imagenes/2017/05/18/uefa/1495075604_388074_1495075972_noticia_normal.jpg</fanart>
</item>
<item>
    <title>FIFA Women's World Cup France 2019: U.S. vs. Chile [COLORyellow]09:00PST[/COLOR]</title>
    <link>
        <sublink>http://cdn3.hdstreams.club/live/ch7/index.m3u8|User-Agent=Mozilla/5.0 (Windows NT 10.0; Win64; x64; rv:67.0) Gecko/20100101 Firefox/67.0&Referer=http://hdstreams.club/page/ch7.php</sublink>
        <sublink>plugin://plugin.video.SportsDevil/?mode=1&amp;amp;item=catcher%3dstreams%26url=http://www.sports-stream.net/ch.php?id=1</sublink>
    </link>
    <thumbnail>https://daily.jstor.org/wp-content/uploads/2015/06/FIFA_Logo_1050x700.jpg</thumbnail>
    <fanart>https://daily.jstor.org/wp-content/uploads/2015/06/FIFA_Logo_1050x700.jpg</fanart>
</item>
<item>
    <title>UEFA Under-21 Euro Soccer 2019: Italy vs. Spain [COLORyellow]11:50PST[/COLOR]</title>
    <link>
        <sublink>plugin://plugin.video.SportsDevil/?mode=1&amp;amp;item=catcher%3dstreams%26url=http://www.sports-stream.net/ch.php?id=1</sublink>
    </link>
    <thumbnail>https://daily.jstor.org/wp-content/uploads/2015/06/FIFA_Logo_1050x700.jpg</thumbnail>
    <fanart>https://daily.jstor.org/wp-content/uploads/2015/06/FIFA_Logo_1050x700.jpg</fanart>
</item>